dpkt/__init__.py
dpkt/ah.py
dpkt/aim.py
dpkt/aoe.py
dpkt/aoeata.py
dpkt/aoecfg.py
dpkt/arp.py
dpkt/asn1.py
dpkt/bgp.py
dpkt/cdp.py
dpkt/compat.py
dpkt/crc32c.py
dpkt/dhcp.py
dpkt/diameter.py
dpkt/dns.py
dpkt/dpkt.py
dpkt/dtp.py
dpkt/edp.py
dpkt/esp.py
dpkt/ethernet.py
dpkt/gre.py
dpkt/gzip.py
dpkt/h225.py
dpkt/hsrp.py
dpkt/http.py
dpkt/http2.py
dpkt/icmp.py
dpkt/icmp6.py
dpkt/ieee80211.py
dpkt/igmp.py
dpkt/ip.py
dpkt/ip6.py
dpkt/ipip.py
dpkt/ipx.py
dpkt/llc.py
dpkt/loopback.py
dpkt/mrt.py
dpkt/netbios.py
dpkt/netflow.py
dpkt/ntp.py
dpkt/ospf.py
dpkt/pcap.py
dpkt/pcapng.py
dpkt/pim.py
dpkt/pmap.py
dpkt/ppp.py
dpkt/pppoe.py
dpkt/qq.py
dpkt/radiotap.py
dpkt/radius.py
dpkt/rfb.py
dpkt/rip.py
dpkt/rpc.py
dpkt/rtp.py
dpkt/rx.py
dpkt/sccp.py
dpkt/sctp.py
dpkt/sip.py
dpkt/sll.py
dpkt/sll2.py
dpkt/smb.py
dpkt/snoop.py
dpkt/ssl.py
dpkt/ssl_ciphersuites.py
dpkt/stp.py
dpkt/stun.py
dpkt/tcp.py
dpkt/telnet.py
dpkt/tftp.py
dpkt/tns.py
dpkt/tpkt.py
dpkt/udp.py
dpkt/utils.py
dpkt/vrrp.py
dpkt/yahoo.py
dpkt-1.9.7.2.dist-info/AUTHORS
dpkt-1.9.7.2.dist-info/LICENSE
dpkt-1.9.7.2.dist-info/METADATA
dpkt-1.9.7.2.dist-info/WHEEL
dpkt-1.9.7.2.dist-info/top_level.txt
dpkt-1.9.7.2.dist-info/RECORD
